chapterize/audiobookshelf.py
chapterize/const.py
chapterize/main.py
chapterize/metadata.py
chapterize/transcribe.py
chapterize/utils.py
chapterize_whisper-0.3.0.dist-info/METADATA
chapterize_whisper-0.3.0.dist-info/WHEEL
chapterize_whisper-0.3.0.dist-info/entry_points.txt
chapterize_whisper-0.3.0.dist-info/RECORD
