Metadata-Version: 2.1
Name: chapterize-whisper
Version: 0.3.0
Summary: 
Author: Jeff Stein
Author-email: jeffstein@gmail.com
Requires-Python: >=3.10,<4.0
Classifier: Programming Language :: Python :: 3
Classifier: Programming Language :: Python :: 3.10
Classifier: Programming Language :: Python :: 3.11
Classifier: Programming Language :: Python :: 3.12
Classifier: Programming Language :: Python :: 3.13
Requires-Dist: aiofiles (>=24.1.0,<25.0.0)
Requires-Dist: click (>=8.1.8,<9.0.0)
Requires-Dist: faster-whisper (>=1.1.0,<2.0.0)
Requires-Dist: mutagen (>=1.47.0,<2.0.0)
Requires-Dist: pydub (>=0.25.1,<0.26.0)
Requires-Dist: requests (>=2.32.3,<3.0.0)
Requires-Dist: rich (>=13.9.4,<14.0.0)
